{"teams":[{"sport":"Baseball","league":"Minor Lg Base","team":"Camag\u00fcey","city":"","country":"Cuba","level":"1","major":false}],"culture":{"Airport":[{"name":"Ignacio Agramonte International Airport","city":"Camag\u00fcey","subtype":"4 - Regional","type":"Airport","majorType":"Infrastructure"}]},"metro":{"slug":"camaguey","name":"Camag\u00fcey","country":"Cuba","subCountry":"","language":"Spanish","capital":"","gawcClass":"","primaryState":"Camag\u00fcey","state2":"","state3":"","pop":333790,"region":"Latin America","continent":"North America","score":0.6,"lat":0.0,"lon":0.0,"primaryCity":"Camag\u00fcey","primaryCityCountry":"Camag\u00fcey, Cuba","gdp":0.0,"gdpPerCapita":0,"dims":{"majorLeagueTeams":0,"totalTeams":1,"majorSportingEvents":0,"companies":0,"marketCap":0.0,"culturalEvents":0,"universities":0,"topUniHospResearch":0,"museumsLandmarks":0,"portsExchangesInfra":0,"airportScore":1.0,"luxuryStars":0.0,"metroStations":0,"suburbStations":0,"trainHubs":0,"skyscrapers":0},"naRank":null,"pctOfCountry":6.2,"rank":1603},"dimRanks":{"majorLeagueTeams":null,"totalTeams":"T-845","majorSportingEvents":null,"companies":null,"marketCap":null,"culturalEvents":null,"universities":null,"topUniHospResearch":null,"museumsLandmarks":null,"portsExchangesInfra":null,"airportScore":"T-332","luxuryStars":null,"metroStations":null,"suburbStations":null,"trainHubs":null,"skyscrapers":null}}