{"universities":[{"rank":861,"name":"University of Concepci\u00f3n","city":"Concepcion","country":"Chile"}],"culture":{"Airport":[{"name":"Carriel Sur International Airport","city":"Concepci\u00f3n","subtype":"4 - Regional","type":"Airport","majorType":"Infrastructure"}],"Suburban Rail":[{"name":"Biotren","city":"Concepcion","subtype":"Suburban Rail","type":"Suburban Rail","majorType":"Infrastructure"},{"name":"Corto Laja","city":"Concepcion","subtype":"Suburban Rail","type":"Suburban Rail","majorType":"Infrastructure"}]},"football":{"total":3,"byLevel":{"1":1,"0":2}},"teams":[{"sport":"Soccer","league":"Chile","team":"Huachipato","city":"Concepcion","country":"Chile","level":"1","major":false}],"metro":{"slug":"concepcion","name":"Concepcion","country":"Chile","subCountry":"","language":"Spanish","capital":"","gawcClass":"","primaryState":"Biob\u00edo","state2":"","state3":"","pop":1072096,"region":"Latin America","continent":"South America","score":1.7,"lat":0.0,"lon":0.0,"primaryCity":"Concepcion","primaryCityCountry":"Concepcion, Chile","gdp":0.0,"gdpPerCapita":0,"dims":{"majorLeagueTeams":0,"totalTeams":1,"majorSportingEvents":0,"companies":0,"marketCap":0.0,"culturalEvents":0,"universities":1,"topUniHospResearch":0,"museumsLandmarks":0,"portsExchangesInfra":0,"airportScore":1.0,"luxuryStars":0.0,"metroStations":0,"suburbStations":39,"trainHubs":0,"skyscrapers":0},"naRank":null,"pctOfCountry":3.8,"rank":923},"dimRanks":{"majorLeagueTeams":null,"totalTeams":"T-845","majorSportingEvents":null,"companies":null,"marketCap":null,"culturalEvents":null,"universities":"T-205","topUniHospResearch":null,"museumsLandmarks":null,"portsExchangesInfra":null,"airportScore":"T-332","luxuryStars":null,"metroStations":null,"suburbStations":"T-119","trainHubs":null,"skyscrapers":null}}