{"culture":{"Airport":[{"name":"Owen Roberts International Airport","city":"George Town (CAY)","subtype":"4 - Regional","type":"Airport","majorType":"Infrastructure"}],"Port":[{"name":"Port of\u00a0George Town","city":"Port of\u00a0George Town","subtype":"Passenger","type":"Port","majorType":"Infrastructure"}]},"luxury":[{"name":"Kimpton Seafire Resort + Spa","city":"Cayman Islands","type":"FTG 5-Star"},{"name":"The Ritz-Carlton, Grand Cayman","city":"Cayman Islands","type":"FTG 5-Star"},{"name":"Palm Heights","city":"Cayman Islands","type":"FTG 4-Star"}],"marketCap":{"total":6445448704,"count":2,"top12":[{"name":"Bullish","valuation":5445448704,"source":"Public"},{"name":"Flashbots","valuation":1000000000,"source":"Unicorn"}]},"metro":{"slug":"george-town-cay","name":"George Town (CAY)","country":"Cayman Islands","subCountry":"","language":"English","capital":"XY","gawcClass":"7","primaryState":"George Town","state2":"","state3":"","pop":67187,"region":"Latin America","continent":"North America","score":6.1,"lat":19.2866,"lon":-81.3744,"primaryCity":"George Town (CAY)","primaryCityCountry":"George Town (CAY), Cayman Islands","gdp":0.0,"gdpPerCapita":0,"dims":{"majorLeagueTeams":0,"totalTeams":0,"majorSportingEvents":0,"companies":2,"marketCap":6445448704.0,"culturalEvents":0,"universities":0,"topUniHospResearch":0,"museumsLandmarks":0,"portsExchangesInfra":1,"airportScore":1.0,"luxuryStars":14.0,"metroStations":0,"suburbStations":0,"trainHubs":0,"skyscrapers":0},"naRank":null,"pctOfCountry":100.0,"rank":374},"dimRanks":{"majorLeagueTeams":null,"totalTeams":null,"majorSportingEvents":null,"companies":"T-173","marketCap":"362","culturalEvents":null,"universities":null,"topUniHospResearch":null,"museumsLandmarks":null,"portsExchangesInfra":"T-149","airportScore":"T-332","luxuryStars":"T-97","metroStations":null,"suburbStations":null,"trainHubs":null,"skyscrapers":null}}