{"teams":[{"sport":"Basketball","league":"Int'l Basketball","team":"Zhejiang Golden Bulls","city":"","country":"China","level":"1","major":false},{"sport":"Basketball","league":"Int'l Basketball","team":"Zhejiang Guangsha Lions","city":"","country":"China","level":"1","major":false},{"sport":"W Basketball","league":"Int'l W Basketball","team":"Zhejiang","city":"","country":"China","level":"1","major":false},{"sport":"Soccer","league":"China","team":"Zhejiang Professional FC","city":"Hangzhou","country":"China","level":"1","major":true}],"universities":[{"rank":68,"name":"Zhejiang University","city":"Hangzhou","country":"China"},{"rank":452,"name":"Zhejiang University of Technology","city":"Hangzhou","country":"China"},{"rank":745,"name":"Hangzhou Normal University","city":"Hangzhou","country":"China"},{"rank":801,"name":"Hangzhou Dianzi University","city":"Hangzhou","country":"China"},{"rank":885,"name":"Zhejiang Sci-Tech University","city":"Hangzhou","country":"China"},{"rank":958,"name":"Zhejiang A&F University","city":"Hangzhou","country":"China"},{"rank":1160,"name":"Westlake University","city":"Hangzhou","country":"China"},{"rank":1164,"name":"Zhejiang Gongshang University","city":"Hangzhou","country":"China"}],"culture":{"Agriculture & Extraction":[{"name":"Longjing Tea (GI)","city":"Hangzhou","subtype":"Appellation - Tea/Coffee","type":"Agriculture & Extraction","majorType":"Infrastructure"}],"Airport":[{"name":"Hangzhou Xiaoshan International Airport","city":"Hangzhou","subtype":"1 - Mega Hub","type":"Airport","majorType":"Infrastructure"}],"Bridge/Tunnel/Dam/Canal":[{"name":"Grand Canal (China)","city":"Hangzhou","subtype":"Canal - Historic","type":"Bridge/Tunnel/Dam/Canal","majorType":"Infrastructure"}],"Metro System":[{"name":"Hangzhou Metro","city":"Hangzhou","subtype":"Subway","type":"Metro System","majorType":"Infrastructure","stations":254},{"name":"Shaoxing Metro","city":"Shaoxing","subtype":"Subway","type":"Metro System","majorType":"Infrastructure","stations":40}],"Museum/Landmark":[{"name":"Zhejiang Museum","city":"Hangzhou","subtype":"Art","type":"Museum/Landmark","majorType":"Infrastructure"},{"name":"Zhejiang Museum of Natural History","city":"Hangzhou","subtype":"Science","type":"Museum/Landmark","majorType":"Infrastructure"}],"Suburban Rail":[{"name":"Shaoxing Tourism New Transit railway","city":"Shaoxing","subtype":"Suburban Rail","type":"Suburban Rail","majorType":"Infrastructure","stations":5}],"Trade Venue":[{"name":"Hangzhou Grand Convention and Exhibition Center","city":"Hangzhou","subtype":"Trade Venue","type":"Trade Venue","majorType":"Infrastructure"}],"Train Station":[{"name":"Hangzhou East Station","city":"Hangzhou","subtype":"Intercity Rail Hub","type":"Train Station","majorType":"Infrastructure"}],"Cultural Event":[{"name":"2016 G-20 Hangzhou summit","city":"Hangzhou","subtype":"International Summit","type":"Cultural Event","majorType":"Event"},{"name":"Hangzhou West Lake Expo","city":"Hangzhou","subtype":"Trade Show","type":"Cultural Event","majorType":"Event","annual":true}]},"skyscrapers":{"city":"Shangyu","over150m":1,"over200m":1,"over300m":0},"marketCap":{"total":934556258831,"count":32,"top12":[{"name":"Alibaba","valuation":337261527040,"source":"Public"},{"name":"Zheijiang Geely Holding Group","valuation":143670000000,"source":"Private"},{"name":"Hailiang Group","valuation":81600000000,"source":"Private"},{"name":"NetEase","valuation":75426742272,"source":"Public"},{"name":"Nongfu Spring","valuation":66295248620,"source":"Public"},{"name":"Hikvision","valuation":44539792290,"source":"Public"},{"name":"Geely","valuation":34092758847,"source":"Public"},{"name":"Zhejiang Sanhua Intelligent Controls Co.,Ltd","valuation":28110625911,"source":"Public"},{"name":"Zhejiang Century Huatong","valuation":18596725510,"source":"Public"},{"name":"Bank of Hangzhou","valuation":18066413953,"source":"Public"},{"name":"Rongsheng Petrochemical","valuation":17085988824,"source":"Public"},{"name":"Zhejiang NHU Co., Ltd.","valuation":16315900453,"source":"Public"}]},"football":{"total":4,"byLevel":{"1":1,"0":3}},"metro":{"slug":"hangzhou","name":"Hangzhou","country":"China","subCountry":"","language":"Mandarin","capital":"","gawcClass":"6","primaryState":"Zhejiang","state2":"","state3":"","pop":17206987,"region":"China","continent":"Asia","score":38.5,"lat":30.2741,"lon":120.1551,"primaryCity":"Hangzhou","primaryCityCountry":"Hangzhou, China","gdp":424.5,"gdpPerCapita":24668,"dims":{"majorLeagueTeams":1,"totalTeams":4,"majorSportingEvents":0,"companies":32,"marketCap":934556258831.0,"culturalEvents":2,"universities":8,"topUniHospResearch":2,"museumsLandmarks":3,"portsExchangesInfra":2,"airportScore":5.0,"luxuryStars":0.0,"metroStations":294,"suburbStations":5,"trainHubs":1,"skyscrapers":109},"naRank":null,"pctOfCountry":2.7,"rank":60},"dimRanks":{"majorLeagueTeams":"T-224","totalTeams":"T-238","majorSportingEvents":null,"companies":"T-28","marketCap":"36","culturalEvents":"T-35","universities":"T-20","topUniHospResearch":"T-50","museumsLandmarks":"T-91","portsExchangesInfra":"T-82","airportScore":"T-42","luxuryStars":null,"metroStations":"15","suburbStations":"T-224","trainHubs":"T-45","skyscrapers":"18"}}