{"teams":[{"sport":"Football","league":"Major Venues","team":"Estadio Hernando Siles","city":"La Paz","country":"Bolivia","level":"1","major":true},{"sport":"Soccer","league":"Bolivia","team":"ABB La Paz","city":"La Paz","country":"Bolivia","level":"1","major":false},{"sport":"Soccer","league":"Bolivia","team":"Always Ready","city":"La Paz","country":"Bolivia","level":"1","major":false},{"sport":"Soccer","league":"Bolivia","team":"Bol\u00edvar","city":"La Paz","country":"Bolivia","level":"1","major":false},{"sport":"Soccer","league":"Bolivia","team":"The Strongest","city":"La Paz","country":"Bolivia","level":"1","major":false}],"culture":{"Airport":[{"name":"El Alto International Airport","city":"La Paz","subtype":"4 - Regional","type":"Airport","majorType":"Infrastructure"}],"Museum/Landmark":[{"name":"Tiwanaku","city":"Tiwanaku","subtype":"Archaeology","type":"Museum/Landmark","majorType":"Infrastructure"}],"Sporting Event":[{"name":"1997 Copa America Final","city":"La Paz","subtype":"Football Final","type":"Sporting Event","majorType":"Event"}]},"skyscrapers":{"city":"La Paz","over150m":1,"over200m":0,"over300m":0},"football":{"total":9,"byLevel":{"1":4,"0":5}},"metro":{"slug":"la-paz","name":"La Paz","country":"Bolivia","subCountry":"","language":"Spanish","capital":"XY","gawcClass":"9","primaryState":"La Paz","state2":"","state3":"","pop":2926996,"region":"Latin America","continent":"South America","score":5.4,"lat":-16.4942,"lon":-68.1475,"primaryCity":"La Paz","primaryCityCountry":"La Paz, Bolivia","gdp":0.0,"gdpPerCapita":0,"dims":{"majorLeagueTeams":1,"totalTeams":5,"majorSportingEvents":1,"companies":0,"marketCap":0.0,"culturalEvents":0,"universities":0,"topUniHospResearch":0,"museumsLandmarks":1,"portsExchangesInfra":0,"airportScore":1.0,"luxuryStars":0.0,"metroStations":0,"suburbStations":0,"trainHubs":0,"skyscrapers":1},"naRank":null,"pctOfCountry":39.4,"rank":418},"dimRanks":{"majorLeagueTeams":"T-188","totalTeams":"T-203","majorSportingEvents":"T-89","companies":null,"marketCap":null,"culturalEvents":null,"universities":null,"topUniHospResearch":null,"museumsLandmarks":"T-157","portsExchangesInfra":null,"airportScore":"T-332","luxuryStars":null,"metroStations":null,"suburbStations":null,"trainHubs":null,"skyscrapers":"T-233"}}