{"teams":[{"sport":"Kabaddi","league":"Other Sports","team":"UP Yoddha","city":"","country":"India","level":"1","major":false},{"sport":"T20 Cricket","league":"IPL","team":"Lucknow Super Giants","city":"","country":"India","level":"1","major":true},{"sport":"Test Cricket","league":"Major Venues","team":"Ekana Cricket Stadium","city":"Lucknow","country":"India","level":"1","major":true},{"sport":"W T20 Cricket","league":"Other Women Sports","team":"UP Warriorz Women","city":"","country":"India","level":"1","major":false}],"culture":{"Airport":[{"name":"Chaudhary Charan Singh Airport","city":"Lucknow","subtype":"4 - Regional","type":"Airport","majorType":"Infrastructure"}],"Metro System":[{"name":"Lucknow Metro","city":"Lucknow","subtype":"Subway","type":"Metro System","majorType":"Infrastructure"}],"Suburban Rail":[{"name":"Lucknow-Kanpur Suburban Railway","city":"Lucknow-Kanpur","subtype":"Suburban Rail","type":"Suburban Rail","majorType":"Infrastructure"}]},"metro":{"slug":"lucknow","name":"Lucknow","country":"India","subCountry":"","language":"Hindi","capital":"","gawcClass":"","primaryState":"Uttar Pradesh","pop":4589838,"region":"South Asia","continent":"Asia","score":6.2,"lat":26.847,"lon":80.947,"primaryCity":"Lucknow","primaryCityCountry":"Lucknow, India","gdp":3.8,"gdpPerCapita":834,"dims":{"majorLeagueTeams":2,"totalTeams":4,"majorSportingEvents":0,"companies":0,"marketCap":0.0,"culturalEvents":0,"universities":0,"topUniHospResearch":0,"museumsLandmarks":0,"portsExchangesInfra":0,"airportScore":1.0,"luxuryStars":0.0,"metroStations":21,"suburbStations":16,"trainHubs":0,"skyscrapers":0},"naRank":null,"pctOfCountry":2.0,"rank":371}}