{"football":{"total":1,"byLevel":{"1":1}},"teams":[{"sport":"Soccer","league":"Cameroon","team":"Colombe FC","city":"Sangm\u00e9lima","country":"Cameroon","level":"1","major":false}],"metro":{"slug":"sangmelima","name":"Sangm\u00e9lima","country":"Cameroon","subCountry":"","language":"French","capital":"","gawcClass":"","primaryState":"South","pop":82513,"region":"Africa","continent":"Africa","score":0.3,"lat":0.0,"lon":0.0,"primaryCity":"Sangm\u00e9lima","primaryCityCountry":"Sangm\u00e9lima, Cameroon","gdp":0.0,"gdpPerCapita":0,"dims":{"majorLeagueTeams":0,"totalTeams":1,"majorSportingEvents":0,"companies":0,"marketCap":0.0,"culturalEvents":0,"universities":0,"topUniHospResearch":0,"museumsLandmarks":0,"portsExchangesInfra":0,"airportScore":0.0,"luxuryStars":0.0,"metroStations":0,"suburbStations":0,"trainHubs":0,"skyscrapers":0},"naRank":null,"pctOfCountry":2.9,"rank":2543}}