{"football":{"total":2,"byLevel":{"0":2}},"metro":{"slug":"trujillo","name":"Trujillo","country":"Peru","subCountry":"","language":"Spanish","capital":"","gawcClass":"","primaryState":"La Libertad","pop":1118724,"region":"Latin America","continent":"South America","score":0.4,"lat":0.0,"lon":0.0,"primaryCity":"Trujillo","primaryCityCountry":"Trujillo, Peru","gdp":5.7,"gdpPerCapita":5095,"dims":{"majorLeagueTeams":0,"totalTeams":0,"majorSportingEvents":0,"companies":0,"marketCap":0.0,"culturalEvents":0,"universities":0,"topUniHospResearch":0,"museumsLandmarks":0,"portsExchangesInfra":0,"airportScore":0.0,"luxuryStars":0.0,"metroStations":0,"suburbStations":0,"trainHubs":0,"skyscrapers":0},"naRank":null,"pctOfCountry":1.2,"rank":2020}}