{"teams":[{"sport":"W Football","league":"Sweden","team":"Ume\u00e5 IK","city":"","country":"Sweden","level":"1","major":false}],"universities":[{"rank":368,"name":"Ume\u00e5 University","city":"Ume\u00e5","country":"Sweden"}],"culture":{"Airport":[{"name":"Ume\u00e5 Airport","city":"Ume\u00e5","subtype":"4 - Regional","type":"Airport","majorType":"Infrastructure"}]},"metro":{"slug":"umea","name":"Ume\u00e5","country":"Sweden","subCountry":"","language":"Swedish","capital":"","gawcClass":"","primaryState":"V\u00e4sterbotten","pop":130997,"region":"Europe","continent":"Europe","score":2.5,"lat":63.8285,"lon":20.2706,"primaryCity":"Ume\u00e5","primaryCityCountry":"Ume\u00e5, Sweden","gdp":0.0,"gdpPerCapita":0,"dims":{"majorLeagueTeams":0,"totalTeams":0,"majorSportingEvents":0,"companies":0,"marketCap":0.0,"culturalEvents":0,"universities":1,"topUniHospResearch":1,"museumsLandmarks":0,"portsExchangesInfra":0,"airportScore":1.0,"luxuryStars":0.0,"metroStations":0,"suburbStations":0,"trainHubs":0,"skyscrapers":0},"naRank":null,"pctOfCountry":2.9,"rank":719},"dimRanks":{"majorLeagueTeams":null,"totalTeams":null,"majorSportingEvents":null,"companies":null,"marketCap":null,"culturalEvents":null,"universities":"T-205","topUniHospResearch":"T-98","museumsLandmarks":null,"portsExchangesInfra":null,"airportScore":"T-332","luxuryStars":null,"metroStations":null,"suburbStations":null,"trainHubs":null,"skyscrapers":null}}