{"teams":[{"sport":"Hockey","league":"Minor/Jr/Int'l Hockey","team":"V\u00e4xj\u00f6 Lakers","city":"","country":"Sweden","level":"1","major":false},{"sport":"W Football","league":"Sweden","team":"V\u00e4xj\u00f6 DFF","city":"","country":"Sweden","level":"1","major":false},{"sport":"Soccer","league":"Sweden","team":"\u00d6sters IF","city":"Vaxjo","country":"Sweden","level":"1","major":false}],"culture":{"Airport":[{"name":"V\u00e4xj\u00f6 Airport","city":"V\u00e4xj\u00f6","subtype":"5 - Small","type":"Airport","majorType":"Infrastructure"}]},"football":{"total":1,"byLevel":{"1":1}},"metro":{"slug":"vaxjo","name":"Vaxjo","country":"Sweden","subCountry":"","language":"Swedish","capital":"","gawcClass":"","primaryState":"Kronoberg","state2":"","state3":"","pop":95995,"region":"Europe","continent":"Europe","score":0.9,"lat":0.0,"lon":0.0,"primaryCity":"Vaxjo","primaryCityCountry":"Vaxjo, Sweden","gdp":0.0,"gdpPerCapita":0,"dims":{"majorLeagueTeams":0,"totalTeams":3,"majorSportingEvents":0,"companies":0,"marketCap":0.0,"culturalEvents":0,"universities":0,"topUniHospResearch":0,"museumsLandmarks":0,"portsExchangesInfra":0,"airportScore":0.5,"luxuryStars":0.0,"metroStations":0,"suburbStations":0,"trainHubs":0,"skyscrapers":0},"naRank":null,"pctOfCountry":1.1,"rank":1328},"dimRanks":{"majorLeagueTeams":null,"totalTeams":"T-302","majorSportingEvents":null,"companies":null,"marketCap":null,"culturalEvents":null,"universities":null,"topUniHospResearch":null,"museumsLandmarks":null,"portsExchangesInfra":null,"airportScore":"T-1431","luxuryStars":null,"metroStations":null,"suburbStations":null,"trainHubs":null,"skyscrapers":null}}